MANIFEST.in
README.rst
setup.py
tox.ini
pyproject/__init__.py
pyproject/__version__.py
pyproject/bump_version.py
pyproject/context.py
pyproject/entry_point.py
pyproject/factory.py
pyproject.egg-info/PKG-INFO
pyproject.egg-info/SOURCES.txt
pyproject.egg-info/dependency_links.txt
pyproject.egg-info/entry_points.txt
pyproject.egg-info/namespace_packages.txt
pyproject.egg-info/not-zip-safe
pyproject.egg-info/requires.txt
pyproject.egg-info/top_level.txt
pyproject/_skeleton/.gitignore
pyproject/_skeleton/.travis.yml
pyproject/_skeleton/LICENSE.j2
pyproject/_skeleton/MANIFEST.in
pyproject/_skeleton/Makefile
pyproject/_skeleton/README.md.j2
pyproject/_skeleton/_test_build.py
pyproject/_skeleton/setup.py.j2
pyproject/_skeleton/tox.ini.j2
pyproject/_skeleton/tests/__init__.py
pyproject/_skeleton/tests/test__readme_doctest.py
pyproject/_skeleton/tests/test__{{name}}.py.j2
pyproject/_skeleton/{{name}}/__init__.py
pyproject/_skeleton/{{name}}/__version__.py
tests/test_start_python_project.py
tests/test_start_python_project.pyc