Metadata-Version: 1.1
Name: pyproject
Version: 1.3.0
Summary: Tool for creating new python packages
Home-page: UNKNOWN
Author: Rotem Yaari
Author-email: vmalloc@gmail.com
License: BSD
Platform: UNKNOWN
Classifier: Programming Language :: Python :: 2.7
